Workbook
Name IQ_CH: 110000
Name IQ_CQ: 5000
Name IQ_CY: 10000
Name IQ_DAILY: 500000
Name IQ_FH: 100000
Name IQ_FQ: 500
Name IQ_FY: 1000
Name IQ_LTM: 2000
Name IQ_MONTH: 15000
Name IQ_NTM: 6000
Name IQ_WEEK: 50000
Name IQ_YTD: 3000

Sheet Dashboard
A1: Interview-Ready Tracker
A2: All figures below are formulas over the Deals / Markets sheets; each data row carries its source URL.
D3: Deal type | E3: Count | F3: $bn disclosed
A4: Latest market prints | D4: M&A | E4: =COUNTIF(Deals!H:H,D4) -> 7 | F4: =SUMIF(Deals!H:H,D4,Deals!I:I) -> 37.65
A5: Latest date with data | B5: =IFERROR(LOOKUP(2,1/(Markets!A2:A10000<>""),Markets!A2:A10000),"n/a") -> 2026-10-02 | D5: LBO | E5: =COUNTIF(Deals!H:H,D5) -> 1 | F5: =SUMIF(Deals!H:H,D5,Deals!I:I) -> 0
A6: S&P 500 | B6: =IFERROR(LOOKUP(2,1/(Markets!B2:B10000<>""),Markets!B2:B10000),"n/a") -> 7722.72 | D6: Take-private | E6: =COUNTIF(Deals!H:H,D6) -> 5 | F6: =SUMIF(Deals!H:H,D6,Deals!I:I) -> 6.85
A7: Nasdaq Composite | B7: =IFERROR(LOOKUP(2,1/(Markets!D2:D10000<>""),Markets!D2:D10000),"n/a") -> 27190.86 | D7: RE | E7: =COUNTIF(Deals!H:H,D7) -> 1 | F7: =SUMIF(Deals!H:H,D7,Deals!I:I) -> 8.1
A8: Dow | B8: =IFERROR(LOOKUP(2,1/(Markets!F2:F10000<>""),Markets!F2:F10000),"n/a") -> 51176.96 | D8: Infra | E8: =COUNTIF(Deals!H:H,D8) -> 0 | F8: =SUMIF(Deals!H:H,D8,Deals!I:I) -> 0
A9: Russell 2000 | B9: =IFERROR(LOOKUP(2,1/(Markets!H2:H10000<>""),Markets!H2:H10000),"n/a") -> 2832.89 | D9: Private credit | E9: =COUNTIF(Deals!H:H,D9) -> 0 | F9: =SUMIF(Deals!H:H,D9,Deals!I:I) -> 0
A10: 2y UST % | B10: =IFERROR(LOOKUP(2,1/(Markets!J2:J10000<>""),Markets!J2:J10000),"n/a") -> 4.78 | D10: Fundraise | E10: =COUNTIF(Deals!H:H,D10) -> 0 | F10: =SUMIF(Deals!H:H,D10,Deals!I:I) -> 0
A11: 10y UST % | B11: =IFERROR(LOOKUP(2,1/(Markets!K2:K10000<>""),Markets!K2:K10000),"n/a") -> 5.28 | D11: Exit/IPO | E11: =COUNTIF(Deals!H:H,D11) -> 1 | F11: =SUMIF(Deals!H:H,D11,Deals!I:I) -> 75
A12: 30y UST % | B12: =IFERROR(LOOKUP(2,1/(Markets!L2:L10000<>""),Markets!L2:L10000),"n/a") -> 5.62 | D12: Secondaries | E12: =COUNTIF(Deals!H:H,D12) -> 0 | F12: =SUMIF(Deals!H:H,D12,Deals!I:I) -> 0
A13: Fed funds upper % | B13: =IFERROR(LOOKUP(2,1/(Markets!M2:M10000<>""),Markets!M2:M10000),"n/a") -> 4 | D13: Restructuring | E13: =COUNTIF(Deals!H:H,D13) -> 0 | F13: =SUMIF(Deals!H:H,D13,Deals!I:I) -> 0
A14: WTI $ | B14: =IFERROR(LOOKUP(2,1/(Markets!O2:O10000<>""),Markets!O2:O10000),"n/a") -> 91.11 | D14: Minority/Growth | E14: =COUNTIF(Deals!H:H,D14) -> 0 | F14: =SUMIF(Deals!H:H,D14,Deals!I:I) -> 0
A15: Brent $ | B15: =IFERROR(LOOKUP(2,1/(Markets!N2:N10000<>""),Markets!N2:N10000),"n/a") -> n/a
A17: Deal ledger
A18: Deals logged | B18: =COUNTA(Deals!A2:A100000) -> 15
A19: Disclosed value logged ($bn) | B19: =SUM(Deals!I:I) -> 127.6
A20: …of which ANNOUNCED | B20: =COUNTIF(Deals!C:C,"ANNOUNCED") -> 12
A21: …of which REPORTED / RUMOR | B21: =COUNTIF(Deals!C:C,"REPORTED")+COUNTIF(Deals!C:C,"RUMOR") -> 2

Sheet Deals
A1: date_logged | B1: date_announced | C1: status | D1: deal | E1: acquirer_or_investor | F1: target | G1: sector | H1: deal_type | I1: value_usd_bn | J1: value_local | K1: multiple | L1: premium | M1: consideration | N1: financing | O1: buy_side_advisors | P1: sell_side_advisors | Q1: covered_firms | R1: rationale | S1: source
A2: 2026-10-03 | B2: 2026-09-15 | C2: ANNOUNCED | D2: GE Aerospace / CPP | E2: GE Aerospace | F2: Consolidated Precision Products | G2: Aerospace | H2: M&A | I2: 11.75 | K2: n/d | L2: n/d | M2: Cash | N2: ~$7bn cash + new debt | O2: n/d | P2: n/d | R2: Vertical integration into castings supply chain | S2: https://intellizence.com/insights/merger-and-acquisition/top-5-ma-deals-of-the-week-reshaping-aerospace-software-real-estate-energy-and-banking/
A3: 2026-10-03 | B3: 2026-09-15 | C3: ANNOUNCED | D3: Cegid / Silae | E3: Cegid | F3: Silae | G3: Software | H3: M&A | I3: 11.6 | J3: EUR 10bn | K3: n/d | L3: n/d | M3: All-stock | N3: n/a | O3: n/d | P3: n/d | R3: French HR/payroll/accounting software consolidation | S3: https://intellizence.com/insights/merger-and-acquisition/top-5-ma-deals-of-the-week-reshaping-aerospace-software-real-estate-energy-and-banking/
A4: 2026-10-03 | B4: 2026-09-15 | C4: ANNOUNCED | D4: IRT / Centerspace | E4: Independence Realty Trust | F4: Centerspace | G4: Real estate (multifamily) | H4: RE | I4: 8.1 | K4: n/d | L4: n/d | M4: All-stock | N4: n/a | O4: n/d | P4: n/d | R4: Multifamily REIT scale + geographic diversification | S4: https://intellizence.com/insights/merger-and-acquisition/top-5-ma-deals-of-the-week-reshaping-aerospace-software-real-estate-energy-and-banking/
A5: 2026-10-03 | B5: 2026-09-15 | C5: ANNOUNCED | D5: Tamarack Valley / Headwater | E5: Tamarack Valley Energy | F5: Headwater Exploration | G5: Energy (upstream) | H5: M&A | J5: CAD 10bn | K5: n/d | L5: n/d | M5: All-stock | N5: n/a | O5: n/d | P5: n/d | R5: Largest Clearwater pure-play; 80k+ bbl/d | S5: https://intellizence.com/insights/merger-and-acquisition/top-5-ma-deals-of-the-week-reshaping-aerospace-software-real-estate-energy-and-banking/
A6: 2026-10-03 | B6: 2026-09-15 | C6: ANNOUNCED | D6: EverBank / WaFd | E6: EverBank (reverse merger) | F6: WaFd | G6: Banks | H6: M&A | I6: 3.9 | K6: n/d | L6: n/d | M6: n/d | N6: n/a | O6: n/d | P6: n/d | R6: Digital specialty bank + western regional footprint | S6: https://intellizence.com/insights/merger-and-acquisition/top-5-ma-deals-of-the-week-reshaping-aerospace-software-real-estate-energy-and-banking/
A7: 2026-10-03 | B7: 2026-09-29 | C7: ANNOUNCED | D7: Veritas / Bodycote | E7: Veritas Capital | F7: Bodycote | G7: Industrials | H7: Take-private | I7: 2.45 | J7: GBP 1.85bn incl. debt | K7: n/d | L7: n/d | M7: Cash | N7: n/d | O7: n/d | P7: n/d | R7: UK take-private; CVC withdrew competing interest Sep 29 | S7: https://www.privateequitywire.co.uk/content_channels/deals/
A8: 2026-10-03 | B8: 2026-09-28 | C8: REPORTED | D8: Warburg / Ingenia Communities (raised proposal) | E8: Warburg Pincus | F8: Ingenia Communities | G8: Real estate (retirement living) | H8: Take-private | I8: 1.5 | K8: n/d | L8: n/d | M8: n/d | N8: n/d | O8: n/d | P8: n/d | Q8: warburg-pincus | R8: Australian retirement-living / holiday parks platform | S8: https://www.privateequitywire.co.uk/content_channels/deals/
A9: 2026-10-03 | B9: 2026-10-02 | C9: REPORTED | D9: Cary auction | E9: KKR; Blackstone; Warburg Pincus (bidders) | F9: Cary | G9: Services (auto glass) | H9: LBO | J9: EUR ~3bn (reported) | K9: n/d | L9: n/d | M9: n/d | N9: n/d | O9: n/d | P9: n/d | Q9: kkr;blackstone;warburg-pincus | R9: Sponsor auction for European windshield repair | S9: https://www.bloomberg.com/news/articles/2026-10-02/kkr-blackstone-are-among-suitors-for-windshield-repairer-cary
A10: 2026-10-03 | B10: 2026-08-13 | C10: ANNOUNCED | D10: H&R REIT take-private | E10: Blackstone RE; Crestpoint; PSP | F10: H&R REIT | G10: Real estate (diversified) | H10: Take-private | J10: CAD 6.7bn | K10: n/d | L10: n/d | M10: Cash and equity | N10: n/d | O10: n/d | P10: n/d | Q10: blackstone | R10: Public-to-private REIT arbitrage; close expected Q4 2026 | S10: https://www.stblaw.com/about-us/news/view/2026/08/13/h-r-reit-to-be-acquired-in-c$6.7-billion-transaction
A11: 2026-10-03 | B11: 2026-04 | C11: ANNOUNCED | D11: Ares / Whitestone REIT | E11: Ares Management | F11: Whitestone REIT | G11: Real estate (retail) | H11: Take-private | I11: 1.7 | K11: n/d | L11: n/d | M11: Cash ($19.00/sh) | N11: n/d | O11: n/d | P11: n/d | Q11: ares | R11: Sunbelt necessity retail via public-to-private | S11: https://www.kirkland.com/news/press-release/2026/04/kirkland-advises-ares-on-1-7-billion-acquisition-of-whitestone-reit
A12: 2026-10-03 | B12: 2026 | C12: ANNOUNCED | D12: Brookfield / Peakstone Realty | E12: Brookfield | F12: Peakstone Realty Trust | G12: Real estate | H12: Take-private | I12: 1.2 | K12: n/d | L12: n/d | M12: Cash ($21/sh) | N12: n/d | O12: n/d | P12: n/d | Q12: brookfield | R12: REIT take-private (date to verify) | S12: https://ca.marketscreener.com/news/brookfield-to-acquire-peakstone-realty-trust-for-1-2bn-ce7e5bd2d98ff725
A13: 2026-10-03 | B13: 2026-04-13 | C13: ANNOUNCED | D13: PWP / Gleacher Shacklock | E13: Perella Weinberg Partners | F13: Gleacher Shacklock | G13: Financials (advisory) | H13: M&A | J13: n/d | K13: n/d | L13: n/d | M13: n/d | N13: n/d | O13: n/d | P13: n/d | Q13: perella-weinberg | R13: UK coverage + cross-border reach | S13: https://www.bloomberg.com/news/articles/2026-04-13/perella-weinberg-agrees-to-buy-uk-boutique-gleacher-shacklock
A14: 2026-10-03 | B14: 2026-06-12 | C14: COMPLETED | D14: SpaceX IPO | E14: Public markets | F14: SpaceX | G14: Aerospace / AI | H14: Exit/IPO | I14: 75 | M14: $135/sh | N14: n/a | O14: n/d | P14: n/d | R14: Largest IPO ever; ~$2.1tn day-1 market cap | S14: https://cdn2.benzinga.com/markets/ipos/26/06/53180108/spacex-stock-closes-up-19-in-record-shattering-ipo-debut
A15: 2026-10-03 | B15: 2026-07 | C15: ANNOUNCED | D15: Taylor Morrison sale to Berkshire Hathaway | E15: Berkshire Hathaway | F15: Taylor Morrison | G15: Homebuilders | H15: M&A | I15: 8.5 | K15: n/d | L15: n/d | M15: n/d | N15: n/d | O15: n/d | P15: Moelis (per Moelis Q2 call; side to verify) | Q15: moelis | R15: Long-duration bet on US housing shortage | S15: https://www.nasdaq.com/articles/moelis-company-q2-earnings-call-highlights
A16: 2026-10-03 | B16: 2025-11 | C16: ANNOUNCED | D16: Adobe / Semrush | E16: Adobe | F16: Semrush | G16: Software | H16: M&A | I16: 1.9 | K16: n/d | L16: n/d | M16: Cash ($12.00/sh) | N16: n/d | O16: n/d | P16: Centerview (exclusive) | Q16: centerview | R16: SEO/marketing data into Experience Cloud | S16: https://www.goodwinlaw.com/en/news-and-events/news/2025/11/announcements-practices-ma-goodwin-advises-centerview-partners-on-semrush-acquisition

Sheet Markets
A1: date | B1: spx | C1: spx_pct | D1: ndx_comp | E1: ndx_comp_pct | F1: dow | G1: dow_pct | H1: rut | I1: rut_pct | J1: ust2y | K1: ust10y | L1: ust30y | M1: fed_funds_upper | N1: brent | O1: wti | P1: gold | Q1: vix | R1: notes | S1: source
A2: 2026-10-01 | J2: 4.78 | K2: 5.24 | L2: 5.61 | M2: 4 | R2: Fed H.15 constant-maturity yields | S2: https://www.federalreserve.gov/releases/h15/
A3: 2026-10-02 | B3: 7722.72 | C3: 0.73 | D3: 27190.86 | E3: 1.2 | F3: 51176.96 | G3: 0.49 | H3: 2832.89 | I3: 0.94 | K3: 5.28 | L3: 5.62 | M3: 4 | O3: 91.11 | R3: Sep payrolls +29k vs 84k; Oct hike odds 64%->22% | S3: https://finance.yahoo.com/markets/stocks/articles/p-500-nasdaq-dow-end-222859024.html

Sheet MacroEvents
A1: date | B1: category | C1: event | D1: actual | E1: consensus | F1: prior | G1: market_reaction | H1: source
A2: 2026-08-28 | B2: Fed | C2: Warsh Jackson Hole: inflation too high; hikes may be needed | G2: Sep hike odds rose from ~1/3 to 57% | H2: https://npr.org/2026/08/28/nx-s1-5947903/federal-reserve-inflation-jackson-hole-interest-rates
A3: 2026-09-16 | B3: Fed | C3: FOMC hikes 25bp to 3.75-4.00% (first hike since Jul 2023) | D3: 3.75-4.00% | F3: 3.50-3.75% | G3: Dots imply one more 2026 hike | H3: https://fedratecalc.com/fomc-meeting-schedule/september-2026/
A4: 2026-10-01 | B4: ECM | C4: Q3 global M&A $993bn (-41% q/q); YTD $3.9tn (+28%) | D4: 993bn | H4: https://www.globalbankingandfinance.com/global-m-deal-rush-fades-third-quarter-rising-borrowing/
A5: 2026-10-02 | B5: Data | C5: September nonfarm payrolls | D5: +29k | E5: +84k | G5: Stocks up; 10y +4bp to 5.28%; Oct hike odds 64%->22% | H5: https://www.cnbc.com/2026/10/02/treasury-yields-bonds-nonfarm-payrolls.html
A6: 2026-10-02 | B6: Data | C6: Unemployment rate (Sep) | D6: 4.2% | E6: 4.1% | F6: 4.1% | H6: https://www.cnbc.com/2026/10/02/treasury-yields-bonds-nonfarm-payrolls.html

Sheet Firms
A1: slug | B1: name | C1: type | D1: ticker | E1: deals_logged | F1: page
A2: evercore | B2: Evercore | C2: Elite boutique | D2: EVR | E2: =COUNTIF(Deals!$Q:$Q,"*"&A2&"*") -> 0 | F2: firms/evercore.md
A3: centerview | B3: Centerview Partners | C3: Elite boutique | D3: private | E3: =COUNTIF(Deals!$Q:$Q,"*"&A3&"*") -> 1 | F3: firms/centerview.md
A4: pjt | B4: PJT Partners | C4: Elite boutique | D4: PJT | E4: =COUNTIF(Deals!$Q:$Q,"*"&A4&"*") -> 0 | F4: firms/pjt.md
A5: lazard | B5: Lazard | C5: Elite boutique / asset mgmt | D5: LAZ | E5: =COUNTIF(Deals!$Q:$Q,"*"&A5&"*") -> 0 | F5: firms/lazard.md
A6: moelis | B6: Moelis & Company | C6: Elite boutique | D6: MC | E6: =COUNTIF(Deals!$Q:$Q,"*"&A6&"*") -> 1 | F6: firms/moelis.md
A7: perella-weinberg | B7: Perella Weinberg Partners | C7: Elite boutique | D7: PWP | E7: =COUNTIF(Deals!$Q:$Q,"*"&A7&"*") -> 1 | F7: firms/perella-weinberg.md
A8: guggenheim | B8: Guggenheim Securities | C8: Elite boutique | D8: private | E8: =COUNTIF(Deals!$Q:$Q,"*"&A8&"*") -> 0 | F8: firms/guggenheim.md
A9: qatalyst | B9: Qatalyst Partners | C9: Elite boutique (tech) | D9: private | E9: =COUNTIF(Deals!$Q:$Q,"*"&A9&"*") -> 0 | F9: firms/qatalyst.md
A10: goldman-sachs | B10: Goldman Sachs | C10: Bulge bracket | D10: GS | E10: =COUNTIF(Deals!$Q:$Q,"*"&A10&"*") -> 0 | F10: firms/goldman-sachs.md
A11: morgan-stanley | B11: Morgan Stanley | C11: Bulge bracket | D11: MS | E11: =COUNTIF(Deals!$Q:$Q,"*"&A11&"*") -> 0 | F11: firms/morgan-stanley.md
A12: jpmorgan | B12: J.P. Morgan | C12: Bulge bracket | D12: JPM | E12: =COUNTIF(Deals!$Q:$Q,"*"&A12&"*") -> 0 | F12: firms/jpmorgan.md
A13: blackstone | B13: Blackstone | C13: Alt manager: PE / RE / credit | D13: BX | E13: =COUNTIF(Deals!$Q:$Q,"*"&A13&"*") -> 2 | F13: firms/blackstone.md
... A27: ares | B27: Ares Management | C27: Alt manager: credit / RE / PE | D27: ARES | E27: =COUNTIF(Deals!$Q:$Q,"*"&A27&"*") -> 1 | F27: firms/ares.md
